{
  "type": "denm",
  "origin": "self",
  "version": "0.3.0",
  "source_uuid": "uuid14",
  "timestamp": 1574778515425,
  "message": {
    "protocol_version": 1,
    "station_id": 42,
    "management_container": {
      "action_id": {
        "originating_station_id": 41,
        "sequence_number": 1
      },
      "detection_time": 503253332000,
      "reference_time": 503253330000,
      "termination": 1,
      "event_position": {
        "latitude": 486263556,
        "longitude": 224921234,
        "altitude": 20000
      },
      "relevance_distance": 3,
      "relevance_traffic_direction": 2,
      "validity_duration": 600,
      "transmission_interval": 500,
      "station_type": 5,
      "confidence": {
        "position_confidence_ellipse": {
          "semi_major_confidence": 100,
          "semi_minor_confidence": 50,
          "semi_major_orientation": 180
        },
        "altitude": 3
      }
    },
    "situation_container": {
      "information_quality": 1,
      "event_type": {
        "cause": 97,
        "subcause": 0
      },
      "linked_cause": {
        "cause": 1,
        "subcause": 1
      }
    },
    "location_container": {
      "event_speed": 289,
      "event_position_heading": 1806,
      "traces": [
        [
          {
            "path_position": {
              "delta_latitude": 102,
              "delta_longitude": 58,
              "delta_altitude": -10
            },
            "path_delta_time": 19
          },
          {
            "path_position": {
              "delta_latitude": 96,
              "delta_longitude": 42,
              "delta_altitude": -6
            },
            "path_delta_time": 21
          }
        ],
        [
          {
            "path_position": {
              "delta_latitude": 75,
              "delta_longitude": 12,
              "delta_altitude": 3
            },
            "path_delta_time": 20
          },
          {
            "path_position": {
              "delta_latitude": 74,
              "delta_longitude": 11,
              "delta_altitude": 2
            },
            "path_delta_time": 20
          },
          {
            "path_position": {
              "delta_latitude": 73,
              "delta_longitude": 10,
              "delta_altitude": 6
            },
            "path_delta_time": 20
          }
        ]
      ],
      "road_type": 0,
      "confidence": {
        "speed": 3,
        "heading": 2
      }
    },
    "alacarte_container": {
      "lane_position": -1,
      "positioning_solution": 2
    }
  }
}